chemlog/__init__.py
chemlog/__main__.py
chemlog/base_classifier.py
chemlog/build_ontology.py
chemlog/cli.py
chemlog/results.py
chemlog/timestamped_logger.py
chemlog/alg_classification/__init__.py
chemlog/alg_classification/charge_classifier.py
chemlog/alg_classification/peptide_size_classifier.py
chemlog/alg_classification/proteinogenics_classifier.py
chemlog/alg_classification/substructure_classifier.py
chemlog/fol_classification/__init__.py
chemlog/fol_classification/charge_verifier.py
chemlog/fol_classification/fol_utils.py
chemlog/fol_classification/functional_groups_verifier.py
chemlog/fol_classification/model_checking.py
chemlog/fol_classification/msol_to_fol_translator.py
chemlog/fol_classification/peptide_size_verifier.py
chemlog/fol_classification/proteinogenics_verifier.py
chemlog/fol_classification/substruct_verifier.py
chemlog/mona_classification/__init__.py
chemlog/mona_classification/mona_compiler.py
chemlog/mona_classification/mona_model_checker.py
chemlog/mona_classification/peptide_size_mona.py
chemlog/msol/__init__.py
chemlog/msol/msol.py
chemlog/msol/peptide_size.py
chemlog/preprocessing/__init__.py
chemlog/preprocessing/chebi_data.py
chemlog/preprocessing/mol_to_fol.py
chemlog/preprocessing/mol_to_msol.py
chemlog/preprocessing/mol_to_qbf.py
chemlog/preprocessing/pubchem_data.py
chemlog/qbf_classification/__init__.py
chemlog/qbf_classification/peptide_size_qbf.py
chemlog/qbf_classification/qbf.py
chemlog/qbf_classification/qbf_solver.py
chemlog/qbf_classification/qbf_translator.py
chemlog/qbf_classification/qbf_utils.py
chemlog-1.0.5.dist-info/licenses/LICENSE
chemlog-1.0.5.dist-info/METADATA
chemlog-1.0.5.dist-info/WHEEL
chemlog-1.0.5.dist-info/top_level.txt
chemlog-1.0.5.dist-info/RECORD
