Metadata-Version: 2.4
Name: chemlog
Version: 1.0.5
Summary: Peptide classifier for ChEBI / PubChem
Author: sfluegel05
Author-email: simon.fluegel@uos.de
License: GNU General Public License v3.0
License-File: LICENSE
Requires-Dist: fastobo
Requires-Dist: networkx
Requires-Dist: pandas
Requires-Dist: rdkit
Requires-Dist: requests
Requires-Dist: tqdm
Requires-Dist: click
Requires-Dist: gavel
Requires-Dist: numpy>=2.0.0
Requires-Dist: click
Requires-Dist: tqdm
Requires-Dist: multiprocess
Dynamic: author
Dynamic: author-email
Dynamic: description
Dynamic: description-content-type
Dynamic: license
Dynamic: license-file
Dynamic: requires-dist
Dynamic: summary
